CHANGES.rst
MANIFEST.in
Makefile
README.rst
setup.py
buildout/__init__.py
buildout.bootstrap.egg-info/PKG-INFO
buildout.bootstrap.egg-info/SOURCES.txt
buildout.bootstrap.egg-info/dependency_links.txt
buildout.bootstrap.egg-info/entry_points.txt
buildout.bootstrap.egg-info/namespace_packages.txt
buildout.bootstrap.egg-info/not-zip-safe
buildout.bootstrap.egg-info/pbr.json
buildout.bootstrap.egg-info/requires.txt
buildout.bootstrap.egg-info/top_level.txt
buildout/bootstrap/__init__.py
buildout/bootstrap/tests.py