Metadata-Version: 1.1
Name: buildout.bootstrap
Version: 1.4.8
Summary: Buildout extension to download https://bootstrap.pypa.io/bootstrap-buildout.py automatically.
Home-page: http://collective.github.com/buildout.bootstrap
Author: Alex Clark
Author-email: aclark@aclark.net
License: ZPL
Keywords: buildout bootstrap
Platform: UNKNOWN
Classifier: Framework :: Buildout
Classifier: Intended Audience :: Developers
Classifier: Topic :: Software Development :: Build Tools
Classifier: License :: OSI Approved :: Zope Public License
Classifier: Programming Language :: Python :: 2.7
